memoryapi.py
memoryapi-1.0.1.dist-info/METADATA
memoryapi-1.0.1.dist-info/WHEEL
memoryapi-1.0.1.dist-info/RECORD
