Metadata-Version: 2.1
Name: memoryapi
Version: 1.0.1
Summary: Simple library to interact with process memory and threads
Author: Xenely
Requires-Python: >=3.9,<4.0
Classifier: Programming Language :: Python :: 3
Classifier: Programming Language :: Python :: 3.9
Classifier: Programming Language :: Python :: 3.10
Classifier: Programming Language :: Python :: 3.11
